qnn/__init__.py
qnn-0.0.0a0.dist-info/LICENSE
qnn-0.0.0a0.dist-info/METADATA
qnn-0.0.0a0.dist-info/WHEEL
qnn-0.0.0a0.dist-info/top_level.txt
qnn-0.0.0a0.dist-info/RECORD
